agglovar/__init__.py
agglovar/fa.py
agglovar/io.py
agglovar/schema.py
agglovar/seqmatch.py
agglovar/align/__init__.py
agglovar/align/op.py
agglovar/align/score.py
agglovar/bed/__init__.py
agglovar/bed/col.py
agglovar/bed/intersect.py
agglovar/bed/join.py
agglovar/bed/merge.py
agglovar/dev/__init__.py
agglovar/dev/imports.py
agglovar/kmer/__init__.py
agglovar/kmer/plot.py
agglovar/kmer/util.py
agglovar/merge/__init__.py
agglovar/merge/base.py
agglovar/merge/cumulative.py
agglovar/merge/config/__init__.py
agglovar/merge/config/parser.py
agglovar/merge/config/stage.py
agglovar/merge/config/strategy.py
agglovar/merge/om/__init__.py
agglovar/merge/om/_executor_base.py
agglovar/merge/om/_executor_nr.py
agglovar/meta/__init__.py
agglovar/meta/decorators.py
agglovar/meta/descriptors.py
agglovar/pairwise/__init__.py
agglovar/pairwise/base.py
agglovar/pairwise/weights.py
agglovar/pairwise/overlap/__init__.py
agglovar/pairwise/overlap/_const.py
agglovar/pairwise/overlap/_overlap.py
agglovar/pairwise/overlap/_stage.py
agglovar/util/__init__.py
agglovar/util/str.py
agglovar/util/var.py
agglovar-0.0.1.dev8.dist-info/licenses/LICENSE
agglovar-0.0.1.dev8.dist-info/METADATA
agglovar-0.0.1.dev8.dist-info/WHEEL
agglovar-0.0.1.dev8.dist-info/top_level.txt
agglovar-0.0.1.dev8.dist-info/RECORD
