Metadata-Version: 2.4
Name: agglovar
Version: 0.0.1.dev8
Summary: Toolkit for fast genomic variant transformations and intersects
License-Expression: MIT
Requires-Python: >=3.12
License-File: LICENSE
Requires-Dist: biopython>=1.85
Requires-Dist: edlib>=1.3.9.post1
Requires-Dist: intervaltree>=3.1.0
Requires-Dist: numpy>=2.3.0
Requires-Dist: ply>=3.11
Requires-Dist: polars[numpy,pandas,pyarrow]>=1.35.2
Provides-Extra: plot
Requires-Dist: matplotlib>=3.10.3; extra == "plot"
Provides-Extra: all
Requires-Dist: agglovar[plot]; extra == "all"
Dynamic: license-file
